Metadata-Version: 2.1
Name: python-can-slcan-disco
Version: 0.1.0
Summary: Python-can slcan driver with discovery
Home-page: https://github.com/yconst/python-can-slcan_disco
Author: Yannis Chatzikonstantinou
Author-email: info@tinymovr.com
Requires-Python: >=3.9
Requires-Dist: python-can
